anomatools/__init__.py
anomatools/models/__init__.py
anomatools/models/_base.py
anomatools/models/_inne.py
anomatools/models/_knno.py
anomatools/models/_ssdo.py
anomatools/models/_ssdo_unsup.py
anomatools/models/_ssknno.py
anomatools/models/scalers/__init__.py
anomatools/models/scalers/_scalers.py
anomatools/utils/__init__.py
anomatools/utils/config.py
anomatools/utils/copkmeans.py
anomatools/utils/plotting.py
anomatools/utils/utils.py
anomatools/utils/validation.py
anomatools-3.0.3.dist-info/LICENSE
anomatools-3.0.3.dist-info/METADATA
anomatools-3.0.3.dist-info/WHEEL
anomatools-3.0.3.dist-info/top_level.txt
anomatools-3.0.3.dist-info/RECORD
