Metadata-Version: 2.1
Name: anomatools
Version: 3.0.3
Summary: A compact toolbox for semi-supervised anomaly detection
Author-email: Vincent Vercruyssen <V.Vercruyssen@egmail.com>
License: Apache License
Project-URL: Homepage, https://github.com/Vincent-Vercruyssen/anomatools
Classifier: Programming Language :: Python :: 3
Classifier: Operating System :: OS Independent
Requires-Python: >=3.8
License-File: LICENSE
